django_faicon-0.1.0.dist-info/METADATA
django_faicon-0.1.0.dist-info/RECORD
django_faicon-0.1.0.dist-info/WHEEL
django_faicon-0.1.0.dist-info/top_level.txt
faicon/__init__.py
faicon/apps.py
faicon/fields.py
faicon/models.py
faicon/urls.py
faicon/views.py
faicon/widgets.py
faicon/static/.DS_Store
faicon/static/faicon/css/faicon.css
faicon/static/faicon/js/faicon.js
faicon/static/faicon/js/list.min.js
faicon/static/fontawesome/.DS_Store
faicon/static/fontawesome/LICENSE.txt
faicon/static/fontawesome/css/all.css
faicon/static/fontawesome/css/all.min.css
faicon/static/fontawesome/css/brands.css
faicon/static/fontawesome/css/brands.min.css
faicon/static/fontawesome/css/fontawesome.css
faicon/static/fontawesome/css/fontawesome.min.css
faicon/static/fontawesome/css/regular.css
faicon/static/fontawesome/css/regular.min.css
faicon/static/fontawesome/css/solid.css
faicon/static/fontawesome/css/solid.min.css
faicon/static/fontawesome/css/svg-with-js.css
faicon/static/fontawesome/css/svg-with-js.min.css
faicon/static/fontawesome/css/v4-shims.css
faicon/static/fontawesome/css/v4-shims.min.css
faicon/static/fontawesome/js/all.js
faicon/static/fontawesome/js/all.min.js
faicon/static/fontawesome/js/brands.js
faicon/static/fontawesome/js/brands.min.js
faicon/static/fontawesome/js/fontawesome.js
faicon/static/fontawesome/js/fontawesome.min.js
faicon/static/fontawesome/js/regular.js
faicon/static/fontawesome/js/regular.min.js
faicon/static/fontawesome/js/solid.js
faicon/static/fontawesome/js/solid.min.js
faicon/static/fontawesome/js/v4-shims.js
faicon/static/fontawesome/js/v4-shims.min.js
faicon/static/fontawesome/metadata/.DS_Store
faicon/static/fontawesome/metadata/icons.yml
faicon/static/fontawesome/webfonts/fa-brands-400.eot
faicon/static/fontawesome/webfonts/fa-brands-400.svg
faicon/static/fontawesome/webfonts/fa-brands-400.ttf
faicon/static/fontawesome/webfonts/fa-brands-400.woff
faicon/static/fontawesome/webfonts/fa-brands-400.woff2
faicon/static/fontawesome/webfonts/fa-regular-400.eot
faicon/static/fontawesome/webfonts/fa-regular-400.svg
