Metadata-Version: 2.1
Name: django-faicon
Version: 0.1.0
Summary: Django Font Awesome 5 icon picker
Home-page: https://github.com/dantium/django-faicon
Author: Dan Atkinson
Author-email: dan@danatkinson.com
License: UNKNOWN
Platform: UNKNOWN
Classifier: Programming Language :: Python :: 3
Classifier: License :: OSI Approved :: MIT License
Classifier: Operating System :: OS Independent
Classifier: Framework :: Django :: 2.1
